pi1wire/__init__.py
pi1wire/_constant.py
pi1wire/_driver.py
pi1wire/_exception.py
pi1wire/_finder.py
pi1wire/_parser.py
pi1wire/_sensor.py
pi1wire/_util.py
pi1wire/py.typed
pi1wire-0.3.0.dist-info/LICENSE.txt
pi1wire-0.3.0.dist-info/METADATA
pi1wire-0.3.0.dist-info/WHEEL
pi1wire-0.3.0.dist-info/top_level.txt
pi1wire-0.3.0.dist-info/RECORD
