Metadata-Version: 2.1
Name: pi1wire
Version: 0.3.0
Summary: 1Wire Sensor Library for Raspberry PI
Home-page: https://github.com/ushiboy/pi1wire
Author: ushiboy
License: MIT
Platform: UNKNOWN
Classifier: Programming Language :: Python :: 3
Classifier: License :: OSI Approved :: MIT License
Classifier: Operating System :: POSIX :: Linux
Requires-Python: >=3.7
